[
    {
        "key": "dbln",
        "value": "%7B%2261550914227339%22%3A%22PW27T2Gt%22%7D",
        "domain": "facebook.com",
        "path": "/login/device-based/",
        "hostOnly": false,
        "creation": "2025-10-15T13:55:21.770Z",
        "lastAccessed": "2025-10-15T13:55:21.771Z"
    },
    {
        "key": "datr",
        "value": "IH3raFsYejVAaW_dwWQqJIrv",
        "domain": "facebook.com",
        "path": "/",
        "hostOnly": false,
        "creation": "2025-10-15T13:55:21.771Z",
        "lastAccessed": "2025-10-15T13:55:21.771Z"
    },
    {
        "key": "sb",
        "value": "IH3raPIs1CEu7UV9X8z4Pa2m",
        "domain": "facebook.com",
        "path": "/",
        "hostOnly": false,
        "creation": "2025-10-15T13:55:21.771Z",
        "lastAccessed": "2025-10-15T13:55:21.771Z"
    },
    {
        "key": "dpr",
        "value": "3",
        "domain": "facebook.com",
        "path": "/",
        "hostOnly": false,
        "creation": "2025-10-15T13:55:21.771Z",
        "lastAccessed": "2025-10-15T13:55:21.771Z"
    },
    {
        "key": "c_user",
        "value": "61550914227339",
        "domain": "facebook.com",
        "path": "/",
        "hostOnly": false,
        "creation": "2025-10-15T13:55:21.771Z",
        "lastAccessed": "2025-10-15T13:55:21.771Z"
    },
    {
        "key": "xs",
        "value": "25%3AnhyAUjowalRoBg%3A2%3A1760263630%3A-1%3A-1",
        "domain": "facebook.com",
        "path": "/",
        "hostOnly": false,
        "creation": "2025-10-15T13:55:21.771Z",
        "lastAccessed": "2025-10-15T13:55:21.771Z"
    },
    {
        "key": "locale",
        "value": "en_GB",
        "domain": "facebook.com",
        "path": "/",
        "hostOnly": false,
        "creation": "2025-10-15T13:55:21.771Z",
        "lastAccessed": "2025-10-15T13:55:21.771Z"
    },
    {
        "key": "wl_cbv",
        "value": "v2%3Bclient_version%3A2952%3Btimestamp%3A1760263638",
        "domain": "facebook.com",
        "path": "/",
        "hostOnly": false,
        "creation": "2025-10-15T13:55:21.771Z",
        "lastAccessed": "2025-10-15T13:55:21.771Z"
    },
    {
        "key": "fbl_st",
        "value": "101432696%3BT%3A29337727",
        "domain": "facebook.com",
        "path": "/",
        "hostOnly": false,
        "creation": "2025-10-15T13:55:21.771Z",
        "lastAccessed": "2025-10-15T13:55:21.771Z"
    },
    {
        "key": "vpd",
        "value": "v1%3B692x360x3",
        "domain": "facebook.com",
        "path": "/",
        "hostOnly": false,
        "creation": "2025-10-15T13:55:21.771Z",
        "lastAccessed": "2025-10-15T13:55:21.771Z"
    },
    {
        "key": "wd",
        "value": "980x1884",
        "domain": "facebook.com",
        "path": "/",
        "hostOnly": false,
        "creation": "2025-10-15T13:55:21.771Z",
        "lastAccessed": "2025-10-15T13:55:21.771Z"
    },
    {
        "key": "fr",
        "value": "0D3SX4mp0XjDs3xSY.AWdu1lCIWL8qJvlibO8b2HKX8WlBgY4aAwfGF-bYNhDMJVYLaao.Bo630g..AAA.0.0.Bo75b4.AWfdHU6irCN2WtWz8CkqNwLeQ_Y",
        "domain": "facebook.com",
        "path": "/",
        "hostOnly": false,
        "creation": "2025-10-15T13:55:21.771Z",
        "lastAccessed": "2025-10-15T13:55:21.771Z"
    }
        ]            ]
